pygomme/__init__.py
pygomme/correlation.py
pygomme/functions.py
pygomme/gomme.py
pygomme/linearfit.py
pygomme/propagation.py
pygomme/examples/C-report-lr.png
pygomme/examples/C-report.png
pygomme/examples/Ccal-report.png
pygomme/examples/Ccal-report_partial.png
pygomme/examples/Celerite-1.png
pygomme/examples/Celerite-2.png
pygomme/examples/D-report-lr.png
pygomme/examples/D-report.png
pygomme/examples/Fp-report.png
pygomme/examples/Fp-report_partial.png
pygomme/examples/Planck-report.png
pygomme/examples/R-report.png
pygomme/examples/R-report_partial.png
pygomme/examples/R1-hist.png
pygomme/examples/R2-hist.png
pygomme/examples/Re-normal.png
pygomme/examples/Re-uniform.png
pygomme/examples/Rp.png
pygomme/examples/Rpp-partial.png
pygomme/examples/Rpp.png
pygomme/examples/Rps-partial.png
pygomme/examples/Rps.png
pygomme/examples/a-hist.png
pygomme/examples/ab-scatter.png
pygomme/examples/ab2-scatter.png
pygomme/examples/b-hist.png
pygomme/examples/ex1-typeA.py
pygomme/examples/ex2-typeB-Propagation.py
pygomme/examples/ex3-Multimetre.py
pygomme/examples/ex4-Focometrie.py
pygomme/examples/ex5-Calorimetrie.py
pygomme/examples/ex6-Regression-lineaire.py
pygomme/examples/frequence-seuil-12.png
pygomme/examples/frequence-seuil-13.png
pygomme/examples/frequence-seuil-23.png
pygomme/examples/fs-hist.png
pygomme/examples/h-hist.png
pygomme-0.0.7.dist-info/LICENSE
pygomme-0.0.7.dist-info/METADATA
pygomme-0.0.7.dist-info/WHEEL
pygomme-0.0.7.dist-info/top_level.txt
pygomme-0.0.7.dist-info/zip-safe
pygomme-0.0.7.dist-info/RECORD
