Metadata-Version: 2.1
Name: pygomme
Version: 0.0.7
Summary: A simple package for calculating errors propagation
Home-page: UNKNOWN
Author: Marc Albrecht
Author-email: marc.albrecht@free.fr
License: UNKNOWN
Platform: UNKNOWN
Classifier: Programming Language :: Python :: 3
Classifier: Operating System :: OS Independent
Classifier: Development Status :: 3 - Alpha
Classifier: License :: OSI Approved :: MIT License
Classifier: Intended Audience :: Science/Research
Classifier: Intended Audience :: Education
Classifier: Topic :: Scientific/Engineering :: Physics
Requires-Python: >=3.6
Requires-Dist: numpy (>=1.13)
Requires-Dist: scipy
Requires-Dist: matplotlib
Requires-Dist: functools
